apitester/__init__.py
apitester/api_request.py
apitester/api_tester.py
apitester/custom_auth_token.py
fileencoding/__init__.py
fileencoding/file_encoding.py
helpers/__init__.py
helpers/app_logger.py
helpers/dict_helpers.py
helpers/path_helpers.py
tools/__init__.py
tools/custom_decorators.py
tools/main.py
pyopstools-0.4.0.dist-info/LICENSE
pyopstools-0.4.0.dist-info/METADATA
pyopstools-0.4.0.dist-info/WHEEL
pyopstools-0.4.0.dist-info/entry_points.txt
pyopstools-0.4.0.dist-info/top_level.txt
pyopstools-0.4.0.dist-info/RECORD
