Metadata-Version: 2.1
Name: pyopstools
Version: 0.4.0
Summary: DevOps CLI tools
Home-page: https://github.com/adeotek/pyopstools
Author: George Benjamin-Schonberger
Author-email: <george.benjamin@gmail.com>
Keywords: ops,api,tester,tools
Classifier: Environment :: Console
Classifier: Intended Audience :: Developers
Classifier: License :: OSI Approved :: MIT License
Classifier: Development Status :: 3 - Alpha
Classifier: Programming Language :: Python :: 3 :: Only
Classifier: Programming Language :: Python :: 3.7
Classifier: Programming Language :: Python :: 3.8
Classifier: Programming Language :: Python :: 3.9
Classifier: Programming Language :: Python :: 3.10
Classifier: Programming Language :: Python :: 3.11
Classifier: Operating System :: Unix
Classifier: Operating System :: MacOS :: MacOS X
Classifier: Operating System :: Microsoft :: Windows
Requires-Python: >=3.7
License-File: LICENSE
Requires-Dist: colorama
Requires-Dist: termcolor
Requires-Dist: requests
Requires-Dist: click
Requires-Dist: charset-normalizer
Provides-Extra: dev
Requires-Dist: check-manifest ; extra == 'dev'
